ranktreeEnsemble/__init__.py
ranktreeEnsemble/functions.py
ranktreeEnsemble/main.py
ranktreeEnsemble/Method/__init__.py
ranktreeEnsemble/Method/ranktreeMethod.py
ranktreeEnsemble/data/__init__.py
ranktreeEnsemble/data/dataPrep.py
ranktreeEnsemble-0.1.3.dist-info/LICENSE
ranktreeEnsemble-0.1.3.dist-info/METADATA
ranktreeEnsemble-0.1.3.dist-info/WHEEL
ranktreeEnsemble-0.1.3.dist-info/top_level.txt
ranktreeEnsemble-0.1.3.dist-info/RECORD
